salary_setter/__init__.py
salary_setter/setter.py
salary_setter_package-0.0.1.dist-info/METADATA
salary_setter_package-0.0.1.dist-info/WHEEL
salary_setter_package-0.0.1.dist-info/top_level.txt
salary_setter_package-0.0.1.dist-info/RECORD
