Metadata-Version: 2.1
Name: salary-setter-package
Version: 0.0.1
Summary: This package includes two functions that calculates both increasement or decreasement of values.
Home-page: UNKNOWN
Author: João Gabriel Barbosa
Author-email: joaogcb29@gmail.com
License: UNKNOWN
Platform: UNKNOWN
Requires-Python: >=3.0
